proofdock/rp/core/__init__.py
proofdock/rp/core/chaos.py
proofdock/rp/core/config.py
proofdock/rp/core/dice.py
proofdock/rp/core/executor.py
proofdock/rp/core/inject.py
proofdock/rp/core/loader.py
proofdock/rp/core/model.py
proofdock/rp/core/parse.py
proofdock/rp/core/version.py
proofdock/rp/core/proofdock/__init__.py
proofdock/rp/core/proofdock/loader.py
proofdock/rp/core/proofdock/session.py
proofdock_reliability_platform_core-1.0.1.dist-info/METADATA
proofdock_reliability_platform_core-1.0.1.dist-info/WHEEL
proofdock_reliability_platform_core-1.0.1.dist-info/top_level.txt
proofdock_reliability_platform_core-1.0.1.dist-info/RECORD
